{
  "Changes": [
    {
      "Action": "EditData",
      "Target": "Data/Objects",
      "Entries": {
        "Cornucopia_AvocadoMayonnaise": {
          "Name": "Cornucopia_AvocadoMayonnaise",
          "Category": -26,
          "SpriteIndex": 120,
          "DisplayName": "{{i18n:AvocadoMayonnaise_name}}",
          "Description": "{{i18n:AvocadoMayonnaise_description}}",
          "Texture": "Cornucopia.ArtisanMachines/Objects",
          "Price": 300,
          "Edibility": 20,
		  "IsDrink": true,
          "ContextTags": [
            "color_green",
            "mayo_item"
          ]
        },
        "Cornucopia_AvocadoOil": {
          "Name": "Cornucopia_AvocadoOil",
          "Category": -26,
          "SpriteIndex": 131,
          "DisplayName": "{{i18n:AvocadoOil_name}}",
          "Description": "{{i18n:AvocadoOil_description}}",
          "Texture": "Cornucopia.ArtisanMachines/Objects",
          "Price": 400,
          "Edibility": 5,
		  "IsDrink": true,
          "ContextTags": [
            "color_green",
            "oil_item"
          ]
        },
        "Cornucopia_BlackPepperMayonnaise": {
          "Name": "Cornucopia_BlackPepperMayonnaise",
          "Category": -26,
          "SpriteIndex": 123,
          "DisplayName": "{{i18n:BlackPepperMayonnaise_name}}",
          "Description": "{{i18n:BlackPepperMayonnaise_description}}",
          "Texture": "Cornucopia.ArtisanMachines/Objects",
          "Price": 220,
          "Edibility": 20,
		  "IsDrink": true,
          "ContextTags": [
            "color_white",
            "mayo_item"
          ]
        },
        "Cornucopia_BrinedOlives": {
          "Name": "Cornucopia_BrinedOlives",
          "Category": -26,
          "SpriteIndex": 0,
          "DisplayName": "{{i18n:BrinedOlives_name}}",
          "Description": "{{i18n:BrinedOlives_description}}",
          "Texture": "Cornucopia.ArtisanMachines/Objects",
          "Price": 100,
          "Edibility": -300,
          "ContextTags": [
            "color_dark_green"
          ]
        },
        "Cornucopia_CocoaButter": {
          "Name": "Cornucopia_CocoaButter",
          "Category": -26,
          "SpriteIndex": 20,
          "DisplayName": "{{i18n:CocoaButter_name}}",
          "Description": "{{i18n:CocoaButter_description}}",
          "Texture": "Cornucopia.ArtisanMachines/Objects",
          "Price": 250,
          "Edibility": -300,
          "ContextTags": [
            "color_sand",
            "butter_item"
          ]
        },
        "Cornucopia_MisoPaste": {
          "Name": "Cornucopia_MisoPaste",
          "Category": -26,
          "SpriteIndex": 87,
          "DisplayName": "{{i18n:MisoPaste_name}}",
          "Description": "{{i18n:MisoPaste_description}}",
          "Texture": "Cornucopia.ArtisanMachines/Objects",
          "Price": 275,
          "Edibility": -300,
          "ContextTags": [
            "color_dark_yellow"
          ]
        },
        "Cornucopia_OliveOilMayonnaise": {
          "Name": "Cornucopia_OliveOilMayonnaise",
          "Category": -26,
          "SpriteIndex": 121,
          "DisplayName": "{{i18n:OliveOilMayonnaise_name}}",
          "Description": "{{i18n:OliveOilMayonnaise_description}}",
          "Texture": "Cornucopia.ArtisanMachines/Objects",
          "Price": 220,
          "Edibility": 20,
		  "IsDrink": true,
          "ContextTags": [
            "color_yellow_green",
            "mayo_item"
          ]
        },
        "Cornucopia_Paprika": {
          "Name": "Cornucopia_Paprika",
          "Category": -26,
          "SpriteIndex": 79,
          "DisplayName": "{{i18n:Paprika_name}}",
          "Description": "{{i18n:Paprika_description}}",
          "Texture": "Cornucopia.ArtisanMachines/Objects",
          "Price": 150,
          "Edibility": -300,
          "ContextTags": [
            "color_red",
            "spice_item"
          ]
        },
        "Cornucopia_PeanutButter": {
          "Name": "Cornucopia_PeanutButter",
          "Category": -26,
          "SpriteIndex": 19,
          "DisplayName": "{{i18n:PeanutButter_name}}",
          "Description": "{{i18n:PeanutButter_description}}",
          "Texture": "Cornucopia.ArtisanMachines/Objects",
          "Price": 200,
          "Edibility": -300,
          "ContextTags": [
            "color_brown",
            "nut_butter_item"
          ]
        },
        "Cornucopia_Pepper": {
          "Name": "Cornucopia_Pepper",
          "Category": -26,
          "SpriteIndex": 83,
          "DisplayName": "{{i18n:Pepper_name}}",
          "Description": "{{i18n:Pepper_description}}",
          "Texture": "Cornucopia.ArtisanMachines/Objects",
          "Price": 180,
          "Edibility": -300,
          "ContextTags": [
            "color_black",
            "spice_item"
          ]
        },
        "Cornucopia_PickleSpears": {
          "Name": "Cornucopia_PickleSpears",
          "Category": -26,
          "SpriteIndex": 0,
          "DisplayName": "{{i18n:PickleSpears_name}}",
          "Description": "{{i18n:PickleSpears_description}}",
          "Texture": "Cornucopia.ArtisanMachines/Objects",
          "Price": 100,
          "Edibility": -300,
          "ContextTags": [
            "color_dark_green",
            "pickle_item"
          ]
        },
        "Cornucopia_StinkyTofu": {
          "Name": "Cornucopia_StinkyTofu",
          "Category": -26,
          "SpriteIndex": 0,
          "DisplayName": "{{i18n:StinkyTofu_name}}",
          "Description": "{{i18n:StinkyTofu_description}}",
          "Texture": "Cornucopia.ArtisanMachines/Objects",
          "Price": 400,
          "Edibility": 5,
          "ContextTags": [
            "color_white",
            "pickle_item"
          ]
        },
        "Cornucopia_SoyButter": {
          "Name": "Cornucopia_SoyButter",
          "Category": -26,
          "SpriteIndex": 24,
          "DisplayName": "{{i18n:SoyButter_name}}",
          "Description": "{{i18n:SoyButter_description}}",
          "Texture": "Cornucopia.ArtisanMachines/Objects",
          "Price": 230,
          "Edibility": -300,
          "ContextTags": [
            "color_sand",
            "nut_butter_item"
          ]
        },
        "Cornucopia_SoyMilk": {
          "Name": "Cornucopia_SoyMilk",
          "Category": -26,
          "SpriteIndex": 158,
          "DisplayName": "{{i18n:SoyMilk_name}}",
          "Description": "{{i18n:SoyMilk_description}}",
          "Texture": "Cornucopia.ArtisanMachines/Objects",
          "Price": 180,
          "Edibility": 20,
		  "IsDrink": true,
          "ContextTags": [
            "color_white",
            "milk_item",
            "plant_milk_item"
          ]
        },
        "Cornucopia_SoySauce": {
          "Name": "Cornucopia_SoySauce",
          "Category": -26,
          "SpriteIndex": 140,
          "DisplayName": "{{i18n:SoySauce_name}}",
          "Description": "{{i18n:SoySauce_description}}",
          "Texture": "Cornucopia.ArtisanMachines/Objects",
          "Price": 300,
          "Edibility": -300,
          "ContextTags": [
            "color_dark_brown",
            "dye_strong"
          ]
        },
        "Cornucopia_ChocolateYogurt": {
          "Name": "Cornucopia_ChocolateYogurt",
          "Category": -26,
          "SpriteIndex": 155,
          "DisplayName": "{{i18n:ChocolateYogurt_name}}",
          "Description": "{{i18n:ChocolateYogurt_description}}",
          "Texture": "Cornucopia.ArtisanMachines/Objects",
          "Price": 350,
          "Edibility": 15,
		  "IsDrink": true,
          "ContextTags": [
            "color_brown",
            "yogurt_item"
          ]
        },
        "Cornucopia_VanillaYogurt": {
          "Name": "Cornucopia_VanillaYogurt",
          "Category": -26,
          "SpriteIndex": 99,
          "DisplayName": "{{i18n:VanillaYogurt_name}}",
          "Description": "{{i18n:VanillaYogurt_description}}",
          "Texture": "Cornucopia.ArtisanMachines/Objects",
          "Price": 350,
          "Edibility": 15,
		  "IsDrink": true,
          "ContextTags": [
            "color_purple",
            "yogurt_item"
          ]
        },
        "Cornucopia_Zoodles": {
          "Name": "Cornucopia_Zoodles",
          "Category": -26,
          "SpriteIndex": 69,
          "DisplayName": "{{i18n:Zoodles_name}}",
          "Description": "{{i18n:Zoodles_description}}",
          "Texture": "Cornucopia.ArtisanMachines/Objects",
          "Price": 275,
          "Edibility": -300,
          "ContextTags": [
            "color_green",
            "noodle_item"
          ]
        }
      }
    }
  ]
}