{
	"Changes":
	[
		// add custom context tags
		{
			"Action": "EditData",
			"Target": "Data/ObjectContextTags",
			"Entries": {
				//produce
				"Adzuki Bean": "color_dark_red, season_summer",
				"Agave": "color_green, season_spring, dye_medium",
				"Asparagus": "color_green, season_summer",
				"Bamboo": "color_yellow, season_spring, season_summer, dye_medium",
				"Barley": "color_brown",
				"Bell Pepper": "color_red, season_fall, dye_medium",
				"Black Beans": "color_dark_purple, season_fall, dye_strong",
				"Blue Agave": "color_blue, season_summer",
				"Broccoli": "color_dark_green, season_fall",
				"Buckwheat": "color_sand",
				"Butternut Squash": "color_yellow, season_summer",
				"Cabbage": "color_green, season_spring",
				"Canary Melon": "color_yellow, season_spring, dye_strong",
				"Canola Flower": "color_yellow, season_spring, season_summer",
				"Cantaloupe": "color_yellow_green, season_spring",
				"Carrot": "color_orange, season_fall, dye_medium",
				"Cassava": "color_brown, season_summer",
				"Celery": "color_green, season_fall",
				"Chickpea": "color_sand, season_summer",
				"Cotton Boll": "color_white, season_summer, season_fall",
				"Cucumber": "color_dark_green, season_summer",
				"Daikon": "color_white, season_fall",
				"Durum": "color_sand",
				"Elderberries": "color_dark_purple, season_winter, dye_strong",
				"Ginseng": "color_sand, season_spring, season_winter",
				"Gooseberry": "color_dark_red, season_summer",
				"GreenPeas": "color_green, season_summer",
				"Habanero": "color_orange, season_fall, dye_medium",
				"Honeydew": "color_yellow_green, season_summer",
				"Jalapeno": "color_green, season_fall, dye_medium",
				"Juniper Berries": "color_dark_blue, season_winter",
				"Kidney Beans": "color_dark_red, season_fall",
				"Kiwi": "color_lime_green, season_summer, dye_medium",
				"Lettuce": "color_green, season_summer",
				"Navy Beans": "color_sand, season_summer",
				"Oats": "color_sand, nut_soap_item",
				"Okra": "color_green, season_summer, season_fall",
				"Onion": "color_dark_yellow, season_spring",
				"Passion Fruit": "color_pink, season_spring, dye_strong",
				"Peanut": "color_brown, season_fall, dye_medium",
				"Pinto Beans": "color_brown, season_spring",
				"Quinoa": "color_sand, season_summer",
				"Raspberry": "color_dark_red, season_summer, dye_strong",
				"Red Onion": "color_dark_red, season_spring",
				"Shallot": "color_salmon, season_spring",
				"Shiitake": "color_brown, season_spring, season_fall",
				"Soybean": "color_green, season_fall",
				"Spinach": "color_dark_green, season_spring, season_fall, dye_medium",
				"SugarBeet": "color_white, season_spring",
				"Sugar Cane": "color_dark_purple, season_summer",
				"Sulfur Shelf": "color_brown, season_summer, season_fall",
				"Summer Squash": "color_yellow, season_summer",
				"Sweet Potato": "color_dark_pink, season_fall, dye_medium",
				"Tabasco Pepper": "color_red, season_fall",
				"Wasabi Root": "color_lime, season_summer, dye_strong",
				"Watermelon": "color_dark_green, season_summer, dye_medium",
				"White Grape": "color_green, season_fall",
				"Zucchini": "color_dark_green, season_fall",
				
				//tree produce
				"Almond": "color_sand, season_fall, nut_soap_item",
				"Cashew": "color_sand, season_fall, nut_soap_item",
				"Cinnamon Sticks": "color_copper, season_winter, nut_soap_item",
				"Cocoa Pod": "color_dark_brown, season_spring, dye_strong, nut_soap_item",
				"Pecan": "color_sand, season_fall, nut_soap_item",
				"Pistachio": "color_lime, season_fall, dye_medium, nut_soap_item",
				"Walnut": "color_brown, season_fall, nut_soap_item",
				
				"Avocado": "color_green, season_summer, dye_medium",
				"Breadfruit": "color_lime, season_spring",
				"Dragon Fruit": "color_dark_pink, season_summer, dye_strong",
				"Durian": "color_yellow_green, season_summer",
				"Fig": "color_dark_purple, season_winter, dye_medium",
				"Grapefruit": "color_orange, season_fall",
				"Lemon": "color_yellow, season_spring",
				"Lime": "color_lime, season_spring",
				"Lychee": "color_pink, season_summer, dye_medium",
				"Nectarine": "color_dark_orange, season_summer",
				"Olive": "color_green, season_fall",
				"Papaya": "color_yellow_green, season_summer",
				"Pear": "color_lime, season_winter",
				"Persimmon": "color_dark_orange, season_winter",
				"Plantain": "color_yellow_green, season_summer",
				"Pomelo": "color_green, season_winter",
				"Ume": "color_green, season_summer",
				"Yuzu": "color_yellow, season_winter"
			}
		},
		
		// add custom context tags, vanilla items
		{
			"Action": "EditData",
			"Target": "Data/ObjectContextTags",
			"TextOperations": [
				{
					"Operation": "Append",
					"Target": ["Entries", "Hazelnut"],
					"Value": "nut_soap_item",
					"Delimiter": ", "
				}
			]
		}
	]
}